<?xml version="1.0" encoding="utf-8"?>
<TopologyInfo xmlns:xsd="http://www.w3.org/2001/XMLSchema" xmlns:xsi="http://www.w3.org/2001/XMLSchema-instance">
  <Details Name="UnquarantineWorker" Alias="Unquarantine Worker"
           Driver=""
           SetupDuration="0" TeardownDuration="0" Public="true" DefaultDuration="5">
    <Description>Blueprint for an external tool to unquarantine a resource or blueprint</Description>
    <Categories>
      <!--<Category Name="" SubCategory="" />-->
    </Categories>
    <Scripts>
      <Script Name="Unquarantine" />
    </Scripts>
    <Diagram Zoom="0.95" NodeSize="Medium" />
  </Details>
  <Resources/>
  <Services/>
  <Apps />
</TopologyInfo>